MANIFEST.in
README.md
setup.cfg
setup.py
chars2vec/.DS_Store
chars2vec/__init__.py
chars2vec/model.py
chars2vec.egg-info/PKG-INFO
chars2vec.egg-info/SOURCES.txt
chars2vec.egg-info/dependency_links.txt
chars2vec.egg-info/top_level.txt
chars2vec/__pycache__/__init__.cpython-36.pyc
chars2vec/__pycache__/model.cpython-36.pyc
chars2vec/trained_models/.DS_Store
chars2vec/trained_models/eng_100/model.pkl
chars2vec/trained_models/eng_100/weights.h5
chars2vec/trained_models/eng_150/model.pkl
chars2vec/trained_models/eng_150/weights.h5
chars2vec/trained_models/eng_200/model.pkl
chars2vec/trained_models/eng_200/weights.h5
chars2vec/trained_models/eng_300/model.pkl
chars2vec/trained_models/eng_300/weights.h5
chars2vec/trained_models/eng_50/model.pkl
chars2vec/trained_models/eng_50/weights.h5