Metadata-Version: 1.2
Name: chars2vec
Version: 0.1.7
Summary: Character-based word embeddings model based on RNN
Home-page: https://github.com/IntuitionEngineeringTeam/chars2vec
Author: Vladimir Chikin
Author-email: v4@intuition.engineering
Maintainer: Intuition
Maintainer-email: dev@intuition.engineering
License: Apache License 2.0
Download-URL: https://github.com/IntuitionEngineeringTeam/chars2vec/archive/master.zip
Platform: UNKNOWN
Classifier: Programming Language :: Python :: 2.7
Classifier: Programming Language :: Python :: 3
